[
  {
    "title": "全分辨率遥感影像在线服务",
    "content": "提供多源遥感影像数据的在线检索下载分发服务",
    "image": "../images/yaogan.png"
  },
  {
    "title": "全时段气象资料在线服务",
    "content": "提供地面观测资料和格点预报监测要素可视化分析、下载分发等在线服务",
    "image": "../images/qixiangziliao.png"
  },
  {
    "title": "气象产品展示服务",
    "content": "提供基于生态和农业两大类服务需求的业务及服务产品和专题数据集的可视化展示、在线浏览及下载等在线服务",
    "image": "../images/qixiangchanpin.png"
  },
  {
    "title": "模型算法及专家知识",
    "content": "提供全面的生态及气象农业产品算法库和专家知识的浏览下载等在线服务",
    "image": "../images/suanfa.png"
  }
]